bsaseq/__init__.py
bsaseq/__main__.py
bsaseq/cli.py
bsaseq/analysis/__init__.py
bsaseq/analysis/candidates.py
bsaseq/analysis/windows.py
bsaseq/annotation/__init__.py
bsaseq/annotation/snpeff.py
bsaseq/core/__init__.py
bsaseq/core/models.py
bsaseq/core/stats.py
bsaseq/io/__init__.py
bsaseq/io/readers.py
bsaseq/io/summary.py
bsaseq/io/vcf.py
bsaseq/io/writers.py
bsaseq/plotting/__init__.py
bsaseq/plotting/diagnostics.py
bsaseq/plotting/genome.py
bsaseq/plotting/style.py
bsaseq/utils/__init__.py
bsaseq/utils/errors.py
bsaseq/utils/logging.py
bsaseq/utils/sorting.py
bsaseq/utils/validation.py
bsaseq-1.0.0.dist-info/METADATA
bsaseq-1.0.0.dist-info/WHEEL
bsaseq-1.0.0.dist-info/entry_points.txt
bsaseq-1.0.0.dist-info/licenses/LICENSE
bsaseq-1.0.0.dist-info/RECORD
