Metadata-Version: 2.4
Name: bsaseq
Version: 1.0.0
Summary: Bulk Segregant Analysis for QTL mapping from pooled whole-genome sequencing
Project-URL: Homepage, https://github.com/username/bsaseq
Project-URL: Documentation, https://bsaseq.readthedocs.io
Project-URL: Repository, https://github.com/username/bsaseq
Project-URL: Issues, https://github.com/username/bsaseq/issues
Project-URL: Changelog, https://github.com/username/bsaseq/blob/main/CHANGELOG.md
Author-email: BSAseq Authors <bsaseq@example.com>
Maintainer-email: BSAseq Authors <bsaseq@example.com>
License: MIT
License-File: LICENSE
Keywords: BSA,QTL,bioinformatics,bulk-segregant-analysis,genetics,genomics,sequencing,variant-analysis
Classifier: Development Status :: 4 - Beta
Classifier: Environment :: Console
Classifier: Intended Audience :: Science/Research
Classifier: License :: OSI Approved :: MIT License
Classifier: Operating System :: MacOS
Classifier: Operating System :: OS Independent
Classifier: Operating System :: POSIX :: Linux
Classifier: Programming Language :: Python :: 3
Classifier: Programming Language :: Python :: 3.9
Classifier: Programming Language :: Python :: 3.10
Classifier: Programming Language :: Python :: 3.11
Classifier: Programming Language :: Python :: 3.12
Classifier: Programming Language :: Python :: 3.13
Classifier: Topic :: Scientific/Engineering :: Bio-Informatics
Classifier: Typing :: Typed
Requires-Python: <3.14,>=3.9
Requires-Dist: click>=8.0.0
Requires-Dist: cyvcf2>=0.30.0
Requires-Dist: matplotlib>=3.5.0
Requires-Dist: numpy>=1.21.0
Requires-Dist: pandas>=1.4.0
Requires-Dist: rich>=12.0.0
Requires-Dist: scipy>=1.7.0
Provides-Extra: dev
Requires-Dist: mypy>=1.0.0; extra == 'dev'
Requires-Dist: pandas-stubs; extra == 'dev'
Requires-Dist: pytest-cov>=4.0.0; extra == 'dev'
Requires-Dist: pytest-mock>=3.10.0; extra == 'dev'
Requires-Dist: pytest>=7.0.0; extra == 'dev'
Requires-Dist: ruff>=0.1.0; extra == 'dev'
Provides-Extra: docs
Requires-Dist: myst-parser>=1.0.0; extra == 'docs'
Requires-Dist: sphinx-click>=4.4.0; extra == 'docs'
Requires-Dist: sphinx-rtd-theme>=1.2.0; extra == 'docs'
Requires-Dist: sphinx>=6.0.0; extra == 'docs'
